Metadata-Version: 2.1
Name: awgp-aadhar-pan-extractor
Version: 0.0.2
Summary: extracts Aadhaar and extracts Pan information
Home-page: UNKNOWN
Author: Deepak Singh Chauhan
Author-email: deepaksingh0034602@gmail.com
License: MIT
Keywords: aadhar extracts information
Platform: UNKNOWN
Classifier: Development Status :: 5 - Production/Stable
Classifier: Intended Audience :: Education
Classifier: Operating System :: Microsoft :: Windows :: Windows 10
Classifier: License :: OSI Approved :: MIT License
Classifier: Programming Language :: Python :: 3
License-File: LICENCE.txt
